ics_to_sms.py
ics_to_sms-0.1.dist-info/entry_points.txt
ics_to_sms-0.1.dist-info/licenses/LICENSE
ics_to_sms-0.1.dist-info/WHEEL
ics_to_sms-0.1.dist-info/METADATA
ics_to_sms-0.1.dist-info/RECORD
