Metadata-Version: 2.4
Name: ics_to_sms
Version: 0.1
Summary: Send an SMS for each alarm found in an ICS file.
Author-email: Julien Palard <julien@palard.fr>
License-Expression: MIT
License-File: LICENSE
Requires-Dist: requests
Requires-Dist: ics
Requires-Dist: tox ; extra == "dev"
Requires-Dist: pylint ; extra == "dev"
Requires-Dist: mypy ; extra == "dev"
Requires-Dist: isort ; extra == "dev"
Requires-Dist: black ; extra == "dev"
Requires-Dist: types-requests ; extra == "dev"
Project-URL: Home, https://git.afpy.org/mdk/ics_to_sms
Provides-Extra: dev
